timetester/__init__.py
timetester-1.1.1.dist-info/LICENSE
timetester-1.1.1.dist-info/METADATA
timetester-1.1.1.dist-info/WHEEL
timetester-1.1.1.dist-info/top_level.txt
timetester-1.1.1.dist-info/RECORD
