Metadata-Version: 2.1
Name: timetester
Version: 1.1.1
Summary: Python package to get an average time of your function
Home-page: https://github.com/feimaomiao/timetester
Author: Matthew Lam
Author-email: lcpmatthew@gmail.com
License: UNKNOWN
Platform: UNKNOWN
Classifier: Programming Language :: Python :: 3
Classifier: License :: OSI Approved :: MIT License
Classifier: Operating System :: OS Independent
Requires-Python: >=3.8
Requires-Dist: matplotlib
